trysoma_sdk/__init__.py
trysoma_sdk/agent.py
trysoma_sdk/bridge.py
trysoma_sdk/patterns.py
trysoma_sdk/py.typed
trysoma_sdk/standalone.py
trysoma_sdk-0.0.6.dist-info/METADATA
trysoma_sdk-0.0.6.dist-info/WHEEL
trysoma_sdk-0.0.6.dist-info/RECORD
